dbstudio/fastapi.py
dbstudio/schema.py
dbstudio/starlette.py
dbstudio/static/index.html
dbstudio/static/vite.svg
dbstudio/static/assets/index-CGWSX2pM.js
dbstudio/static/assets/index-CXkX6QG-.css
dbstudio-0.1.1.dist-info/LICENSE
dbstudio-0.1.1.dist-info/METADATA
dbstudio-0.1.1.dist-info/WHEEL
dbstudio-0.1.1.dist-info/top_level.txt
dbstudio-0.1.1.dist-info/RECORD
