Metadata-Version: 2.1
Name: dbstudio
Version: 0.1.1
Summary: Web-based database management tool.
Author-email: Luca Faggianelli <luca@velvetlab.tech>
License: MIT
Keywords: python,db,sqlalchemy,sqlmodel,web-ui,fastapi,starlette,pydantic
Classifier: Programming Language :: Python :: 3
Requires-Python: >=3.9
License-File: LICENSE
Provides-Extra: dev
Requires-Dist: black ==23.10.1 ; extra == 'dev'
Requires-Dist: coverage ==7.3.2 ; extra == 'dev'
Requires-Dist: fastapi >=0.70.0 ; extra == 'dev'
Requires-Dist: flake8 ==6.1.0 ; extra == 'dev'
Requires-Dist: pytest ==7.4.3 ; extra == 'dev'
Requires-Dist: pytest-asyncio ==0.21.1 ; extra == 'dev'
Requires-Dist: pytest-env ==1.1.0 ; extra == 'dev'
Requires-Dist: sqlalchemy >=1.4.0 ; extra == 'dev'
